minty_ddd/__init__.py
minty_ddd/ddd.py
minty_ddd-0.0.5.dist-info/LICENSE
minty_ddd-0.0.5.dist-info/METADATA
minty_ddd-0.0.5.dist-info/WHEEL
minty_ddd-0.0.5.dist-info/top_level.txt
minty_ddd-0.0.5.dist-info/RECORD
