Metadata-Version: 2.1
Name: minty-ddd
Version: 0.0.5
Summary: Minty Command and Query based on DDD
Home-page: https://gitlab.com/minty-python/minty-ddd
Author: Michiel Ootjers
Author-email: michiel@mintlab.nl
License: EUPL license
Keywords: minty_ddd
Platform: UNKNOWN
Classifier: Development Status :: 2 - Pre-Alpha
Classifier: Intended Audience :: Developers
Classifier: License :: OSI Approved :: European Union Public Licence 1.2 (EUPL 1.2)
Classifier: Natural Language :: English
Classifier: Programming Language :: Python :: 3.6
Classifier: Programming Language :: Python :: 3.7
Requires-Dist: black
Requires-Dist: flake8
Requires-Dist: isort
Requires-Dist: sphinx
Requires-Dist: sphinx-rtd-theme
Requires-Dist: sphinx-autodoc-typehints
Requires-Dist: bumpversion
Requires-Dist: minty-infrastructure
